tight_loops/__init__.py
tight_loops/folium_loops.py
tight_loops/tight_loops.py
tight_loops-0.3.1.dist-info/LICENSE
tight_loops-0.3.1.dist-info/METADATA
tight_loops-0.3.1.dist-info/WHEEL
tight_loops-0.3.1.dist-info/dependency_links.txt
tight_loops-0.3.1.dist-info/top_level.txt
tight_loops-0.3.1.dist-info/RECORD
