Metadata-Version: 2.1
Name: tight-loops
Version: 0.3.1
Summary: This is a demo python package for UTK GEOG510
Home-page: https://github.com/wnelso18/tight_loops
Author: Will Nelson
Author-email: wnelso18@vols.utk.edu
License: MIT license
Keywords: tight_loops
Classifier: Development Status :: 2 - Pre-Alpha
Classifier: Intended Audience :: Developers
Classifier: License :: OSI Approved :: MIT License
Classifier: Natural Language :: English
Classifier: Programming Language :: Python :: 3
Classifier: Programming Language :: Python :: 3.7
Classifier: Programming Language :: Python :: 3.8
Classifier: Programming Language :: Python :: 3.9
Classifier: Programming Language :: Python :: 3.10
Requires-Python: >=3.7
License-File: LICENSE
Requires-Dist: folium
Requires-Dist: ipyleaflet
Requires-Dist: geopandas
Requires-Dist: httpx
Requires-Dist: whitebox
